README
setup.py
Flask_Downloader.egg-info/PKG-INFO
Flask_Downloader.egg-info/SOURCES.txt
Flask_Downloader.egg-info/dependency_links.txt
Flask_Downloader.egg-info/namespace_packages.txt
Flask_Downloader.egg-info/not-zip-safe
Flask_Downloader.egg-info/requires.txt
Flask_Downloader.egg-info/top_level.txt
flaskext/__init__.py
flaskext/downloader.py