Metadata-Version: 1.0
Name: Flask-Downloader
Version: 0.1
Summary: Allow a Flask web app to download files on behalf of the user.
Home-page: https://github.com/kblin/flask-downloader
Author: Kai Blin
Author-email: kai@samba.org
License: BSD
Platform: any
Classifier: Development Status :: 4 - Beta
Classifier: Environment :: Web Environment
Classifier: Intended Audience :: Developers
Classifier: License :: OSI Approved :: BSD License
Classifier: Operating System :: OS Independent
Classifier: Programming Language :: Python
Classifier: Topic :: Internet :: WWW/HTTP :: Dynamic Content
Classifier: Topic :: Software Development :: Libraries :: Python Modules
